LICENSE
MANIFEST.in
README.rst
setup.py
ObjectExtractor.egg-info/PKG-INFO
ObjectExtractor.egg-info/SOURCES.txt
ObjectExtractor.egg-info/dependency_links.txt
ObjectExtractor.egg-info/requires.txt
ObjectExtractor.egg-info/top_level.txt
object_extractor/__init__.py
object_extractor/data.py
object_extractor/extractor.py
object_extractor/data/haarcascade_eye.xml
object_extractor/data/haarcascade_eye_tree_eyeglasses.xml
object_extractor/data/haarcascade_frontalcatface.xml
object_extractor/data/haarcascade_frontalcatface_extended.xml
object_extractor/data/haarcascade_frontalface_alt.xml
object_extractor/data/haarcascade_frontalface_alt2.xml
object_extractor/data/haarcascade_frontalface_alt_tree.xml
object_extractor/data/haarcascade_frontalface_default.xml
object_extractor/data/haarcascade_fullbody.xml
object_extractor/data/haarcascade_lefteye_2splits.xml
object_extractor/data/haarcascade_licence_plate_rus_16stages.xml
object_extractor/data/haarcascade_lowerbody.xml
object_extractor/data/haarcascade_profileface.xml
object_extractor/data/haarcascade_righteye_2splits.xml
object_extractor/data/haarcascade_russian_plate_number.xml
object_extractor/data/haarcascade_smile.xml
object_extractor/data/haarcascade_upperbody.xml