Metadata-Version: 1.0
Name: ObjectExtractor
Version: 0.2.2
Summary: Extract objects from images with OpenCV
Home-page: https://github.com/ducthienbui97/ObjectExtractor
Author: Thien Bui
Author-email: thienbui797@gmail.com
License: BSD-3-Clause
Platform: UNKNOWN
